setup.py
lsas/lsas.py
lsas.egg-info/PKG-INFO
lsas.egg-info/SOURCES.txt
lsas.egg-info/dependency_links.txt
lsas.egg-info/top_level.txt