Metadata-Version: 2.1
Name: lsas
Version: 1.0.0
Summary: this is about lsa.
Author: Meng Li
Author-email: 2977997172@qq.com
